worktimecalc/__init__.py
worktimecalc/calc.py
worktimecalc/delta.py
worktimecalc/error_messages.py
worktimecalc-0.1.4.dist-info/LICENSE
worktimecalc-0.1.4.dist-info/METADATA
worktimecalc-0.1.4.dist-info/WHEEL
worktimecalc-0.1.4.dist-info/top_level.txt
worktimecalc-0.1.4.dist-info/RECORD
