Metadata-Version: 2.1
Name: worktimecalc
Version: 0.1.4
Summary: Calculates the business time between two datetimes.
Author: Misao
License: The MIT License (MIT)
Project-URL: Home, https://github.com/MisaoDev/work-time-calc
Keywords: time,calculator,tools,business time,business hours,work hours,work time
Classifier: License :: OSI Approved :: MIT License
Classifier: Programming Language :: Python
Classifier: Programming Language :: Python :: 3
License-File: LICENSE
Provides-Extra: dev
Requires-Dist: pytest ; extra == 'dev'
